{
  "code": "1919",
  "mergers": [
    {
      "merger_id": "MN-01083",
      "merger_name": "Civilmart \u2013 Taylex",
      "is_waiver": false,
      "status": "Assessment completed"
    },
    {
      "merger_id": "WA-60010",
      "merger_name": "Michelin - Flexitallic",
      "is_waiver": true,
      "status": "Assessment completed"
    },
    {
      "merger_id": "MN-85006",
      "merger_name": "Tega and Apollo Funds consortium - Molycop",
      "is_waiver": false,
      "status": "Under assessment"
    }
  ],
  "count": 3
}