{
  "total_mergers": 73,
  "total_waivers": 100,
  "by_status": {
    "Assessment completed": 49,
    "Under assessment": 24
  },
  "by_determination": {
    "Approved": 49,
    "Referred to phase 2": 3
  },
  "by_waiver_determination": {
    "Approved": 93,
    "Not approved": 7
  },
  "phase_duration": {
    "average_days": 27.755102040816325,
    "median_days": 25,
    "average_business_days": 18.040816326530614,
    "median_business_days": 17,
    "percentiles": {
      "day15": {
        "count": 16,
        "percentage": 32.7
      },
      "day20": {
        "count": 40,
        "percentage": 81.6
      },
      "day30": {
        "count": 48,
        "percentage": 98.0
      }
    }
  },
  "top_industries": [
    {
      "name": "Computer System Design and Related Services",
      "count": 24
    },
    {
      "name": "Software Publishing",
      "count": 21
    },
    {
      "name": "Financial Asset Investing",
      "count": 16
    },
    {
      "name": "Other Auxiliary Finance and Investment Services",
      "count": 15
    },
    {
      "name": "Accommodation",
      "count": 8
    },
    {
      "name": "Non-Residential Property Operators",
      "count": 7
    },
    {
      "name": "Scientific Research Services",
      "count": 7
    },
    {
      "name": "Pubs, Taverns and Bars",
      "count": 7
    },
    {
      "name": "Car Retailing",
      "count": 5
    },
    {
      "name": "Cafes and Restaurants",
      "count": 5
    }
  ],
  "recent_mergers": [
    {
      "merger_id": "MN-55013",
      "merger_name": "Lawrence & Hanson - Gordon Macdonald",
      "status": "Under assessment",
      "accc_determination": null,
      "effective_notification_datetime": "2026-04-13T12:00:00Z",
      "is_waiver": false
    },
    {
      "merger_id": "MN-35013",
      "merger_name": "Estia Health \u2013 Norsan residential aged care business",
      "status": "Under assessment",
      "accc_determination": null,
      "effective_notification_datetime": "2026-04-10T12:00:00Z",
      "is_waiver": false
    },
    {
      "merger_id": "MN-40015",
      "merger_name": "Swiss Re - QBE Insurance's Trade Credit and Surety business",
      "status": "Under assessment",
      "accc_determination": null,
      "effective_notification_datetime": "2026-04-10T12:00:00Z",
      "is_waiver": false
    },
    {
      "merger_id": "MN-95011",
      "merger_name": "Dubai Aerospace Enterprise - Macquarie AirFinance",
      "status": "Under assessment",
      "accc_determination": null,
      "effective_notification_datetime": "2026-04-10T12:00:00Z",
      "is_waiver": false
    },
    {
      "merger_id": "MN-20013",
      "merger_name": "Eli Lilly / Orna Therapeutics",
      "status": "Under assessment",
      "accc_determination": null,
      "effective_notification_datetime": "2026-04-08T12:00:00Z",
      "is_waiver": false
    }
  ],
  "recent_determinations": [
    {
      "merger_id": "WA-85021",
      "merger_name": "Yancoal - Kestrel Coal Group",
      "determination": "Approved",
      "determination_date": "2026-04-13T12:00:00Z",
      "page_modified_datetime": "2026-04-13T17:49:56+10:00",
      "determination_type": "final",
      "is_waiver": true,
      "stage": "Waiver application"
    },
    {
      "merger_id": "WA-95010",
      "merger_name": "Lighthouse - Precise Services Group",
      "determination": "Approved",
      "determination_date": "2026-04-13T12:00:00Z",
      "page_modified_datetime": "2026-04-13T17:31:23+10:00",
      "determination_type": "final",
      "is_waiver": true,
      "stage": "Waiver application"
    },
    {
      "merger_id": "MN-40009",
      "merger_name": "Gilead - Arcellx",
      "determination": "Approved",
      "determination_date": "2026-04-13T12:00:00Z",
      "page_modified_datetime": "2026-04-13T17:07:35+10:00",
      "determination_type": "final",
      "is_waiver": false,
      "stage": "Phase 1 - initial assessment"
    },
    {
      "merger_id": "MN-75012",
      "merger_name": "Opal HealthCare \u2013 Greenwich Place residential aged care home",
      "determination": "Approved",
      "determination_date": "2026-04-13T12:00:00Z",
      "page_modified_datetime": "2026-04-13T14:41:36+10:00",
      "determination_type": "final",
      "is_waiver": false,
      "stage": "Phase 1 - initial assessment"
    },
    {
      "merger_id": "MN-30005",
      "merger_name": "Adobe - Semrush",
      "determination": "Approved",
      "determination_date": "2026-04-10T12:00:00Z",
      "page_modified_datetime": "2026-04-13T15:47:05+10:00",
      "determination_type": "final",
      "is_waiver": false,
      "stage": "Phase 1 - initial assessment"
    },
    {
      "merger_id": "WA-45009",
      "merger_name": "Idemitsu - MidOcean Energy",
      "determination": "Approved",
      "determination_date": "2026-04-10T12:00:00Z",
      "page_modified_datetime": "2026-04-10T17:06:36+10:00",
      "determination_type": "final",
      "is_waiver": true,
      "stage": "Waiver application"
    }
  ]
}