{
  "total_mergers": 57,
  "total_waivers": 62,
  "by_status": {
    "Assessment completed": 35,
    "Under assessment": 21,
    "Assessment suspended": 1
  },
  "by_determination": {
    "Approved": 35,
    "Referred to phase 2": 2
  },
  "by_waiver_determination": {
    "Approved": 56,
    "Not approved": 6
  },
  "phase_duration": {
    "average_days": 27.65714285714286,
    "median_days": 25,
    "average_business_days": 17.82857142857143,
    "median_business_days": 17,
    "percentiles": {
      "day15": {
        "count": 10,
        "percentage": 28.6
      },
      "day20": {
        "count": 29,
        "percentage": 82.9
      },
      "day30": {
        "count": 35,
        "percentage": 100.0
      }
    }
  },
  "top_industries": [
    {
      "name": "Software Publishing",
      "count": 19
    },
    {
      "name": "Computer System Design and Related Services",
      "count": 19
    },
    {
      "name": "Financial Asset Investing",
      "count": 9
    },
    {
      "name": "Other Auxiliary Finance and Investment Services",
      "count": 8
    },
    {
      "name": "Non-Residential Property Operators",
      "count": 5
    },
    {
      "name": "Scientific Research Services",
      "count": 4
    },
    {
      "name": "Pharmaceutical and Toiletry Goods Wholesaling",
      "count": 4
    },
    {
      "name": "Pubs, Taverns and Bars",
      "count": 4
    },
    {
      "name": "Data Processing and Web Hosting Services",
      "count": 4
    },
    {
      "name": "Dental Services",
      "count": 4
    }
  ],
  "recent_mergers": [
    {
      "merger_id": "MN-40009",
      "merger_name": "Gilead - Arcellx",
      "status": "Under assessment",
      "accc_determination": null,
      "effective_notification_datetime": "2026-03-19T12:00:00Z",
      "is_waiver": false
    },
    {
      "merger_id": "MN-75012",
      "merger_name": "Opal HealthCare \u2013 Greenwich Place residential aged care home",
      "status": "Under assessment",
      "accc_determination": null,
      "effective_notification_datetime": "2026-03-19T12:00:00Z",
      "is_waiver": false
    },
    {
      "merger_id": "MN-50012",
      "merger_name": "Maas \u2013 50% acquisition of COLAS\u2019 Caloundra asphalt plant and 100% of COLAS\u2019 Tomago asphalt plant",
      "status": "Under assessment",
      "accc_determination": null,
      "effective_notification_datetime": "2026-03-18T12:00:00Z",
      "is_waiver": false
    },
    {
      "merger_id": "MN-65009",
      "merger_name": "CVC Capital Partners \u2013 Marathon Asset Management",
      "status": "Under assessment",
      "accc_determination": null,
      "effective_notification_datetime": "2026-03-18T12:00:00Z",
      "is_waiver": false
    },
    {
      "merger_id": "MN-30005",
      "merger_name": "Adobe - Semrush",
      "status": "Under assessment",
      "accc_determination": null,
      "effective_notification_datetime": "2026-03-16T12:00:00Z",
      "is_waiver": false
    }
  ],
  "recent_determinations": [
    {
      "merger_id": "WA-85014",
      "merger_name": "Genesis Minerals \u2013 Magnetic Resources",
      "determination": "Approved",
      "determination_date": "2026-03-19T12:00:00Z",
      "page_modified_datetime": "2026-03-19T18:48:09+11:00",
      "determination_type": "final",
      "is_waiver": true,
      "stage": "Waiver application"
    },
    {
      "merger_id": "WA-50006",
      "merger_name": "Airtree \u2013 HotDoc",
      "determination": "Approved",
      "determination_date": "2026-03-19T12:00:00Z",
      "page_modified_datetime": "2026-03-19T18:39:40+11:00",
      "determination_type": "final",
      "is_waiver": true,
      "stage": "Waiver application"
    },
    {
      "merger_id": "WA-20007",
      "merger_name": "Telstra \u2013 Infosys Technologies",
      "determination": "Approved",
      "determination_date": "2026-03-19T12:00:00Z",
      "page_modified_datetime": "2026-03-19T18:15:59+11:00",
      "determination_type": "final",
      "is_waiver": true,
      "stage": "Waiver application"
    },
    {
      "merger_id": "WA-20010",
      "merger_name": "PT Asian Bulk Logistics \u2013 Engage Marine",
      "determination": "Not approved",
      "determination_date": "2026-03-19T12:00:00Z",
      "page_modified_datetime": "2026-03-19T18:09:33+11:00",
      "determination_type": "final",
      "is_waiver": true,
      "stage": "Waiver application"
    },
    {
      "merger_id": "MN-85003",
      "merger_name": "North American Construction Group \u2013 Iron Mine Contracting and Iron Hire",
      "determination": "Approved",
      "determination_date": "2026-03-19T12:00:00Z",
      "page_modified_datetime": "2026-03-19T12:58:20+11:00",
      "determination_type": "final",
      "is_waiver": false,
      "stage": "Phase 1 - initial assessment"
    },
    {
      "merger_id": "MN-60007",
      "merger_name": "Craig Mostyn \u2013 Patmore Feeds",
      "determination": "Approved",
      "determination_date": "2026-03-19T12:00:00Z",
      "page_modified_datetime": "2026-03-19T12:04:41+11:00",
      "determination_type": "final",
      "is_waiver": false,
      "stage": "Phase 1 - initial assessment"
    }
  ]
}