{
  "mergers": [
    {
      "merger_id": "WA-90004",
      "merger_name": "Crossmuller \u2013 GEM",
      "status": "Assessment completed",
      "accc_determination": "Approved",
      "is_waiver": true,
      "effective_notification_datetime": "2026-02-16T12:00:00Z",
      "determination_publication_date": "2026-03-05T12:00:00Z",
      "end_of_determination_period": null,
      "stage": "Waiver application",
      "acquirers": [
        {
          "name": "CROSSMULLER PTY. LIMITED",
          "identifier_type": "ABN",
          "identifier": "98 088 327 093"
        }
      ],
      "targets": [
        {
          "name": "GEMCORP Holdings Pty Ltd",
          "identifier_type": "ACN",
          "identifier": "685 947 522"
        }
      ],
      "other_parties": [],
      "anzsic_codes": [
        {
          "code": "2439",
          "name": "Other Electrical Equipment Manufacturing"
        }
      ],
      "url": "https://www.accc.gov.au/public-registers/mergers-and-acquisitions-registers/acquisitions-register/crossmuller-%E2%80%93-gem"
    },
    {
      "merger_id": "WA-95005",
      "merger_name": "HCLTech - Jaspersoft",
      "status": "Assessment completed",
      "accc_determination": "Approved",
      "is_waiver": true,
      "effective_notification_datetime": "2026-02-05T12:00:00Z",
      "determination_publication_date": "2026-02-19T12:00:00Z",
      "end_of_determination_period": null,
      "stage": "Waiver application",
      "acquirers": [
        {
          "name": "HCL Technologies Limited",
          "identifier_type": "ABN",
          "identifier": "37 541 578 951"
        }
      ],
      "targets": [
        {
          "name": "CLOUD SOFTWARE GROUP AUSTRALIA PTY LTD",
          "identifier_type": "ABN",
          "identifier": "94 092 002 321"
        }
      ],
      "other_parties": [],
      "anzsic_codes": [
        {
          "code": "5420",
          "name": "Software Publishing"
        },
        {
          "code": "7000",
          "name": "Computer System Design and Related Services"
        }
      ],
      "url": "https://www.accc.gov.au/public-registers/mergers-and-acquisitions-registers/acquisitions-register/hcltech-jaspersoft"
    },
    {
      "merger_id": "WA-95006",
      "merger_name": "Laundy Group \u2013 Nine Radio",
      "status": "Assessment completed",
      "accc_determination": "Approved",
      "is_waiver": true,
      "effective_notification_datetime": "2026-02-11T12:00:00Z",
      "determination_publication_date": "2026-02-20T12:00:00Z",
      "end_of_determination_period": null,
      "stage": "Waiver application",
      "acquirers": [
        {
          "name": "SPIKE MEDIA PTY LTD",
          "identifier_type": "ABN",
          "identifier": "28 694 712 699"
        }
      ],
      "targets": [
        {
          "name": "NINE RADIO PTY LIMITED",
          "identifier_type": "ABN",
          "identifier": "32 063 906 927"
        }
      ],
      "other_parties": [
        {
          "name": "Arthur Laundy",
          "identifier_type": null,
          "identifier": ""
        },
        {
          "name": "FAIRFAX MEDIA LIMITED",
          "identifier_type": "ABN",
          "identifier": "15 008 663 161"
        },
        {
          "name": "NINE ENTERTAINMENT CO. HOLDINGS LIMITED",
          "identifier_type": "ABN",
          "identifier": "60 122 203 892"
        }
      ],
      "anzsic_codes": [
        {
          "code": "5610",
          "name": "Radio Broadcasting"
        }
      ],
      "url": "https://www.accc.gov.au/public-registers/mergers-and-acquisitions-registers/acquisitions-register/laundy-group-%E2%80%93-nine-radio"
    },
    {
      "merger_id": "WA-95008",
      "merger_name": "Vets Central \u2013 West Toowoomba Veterinary Surgery in QLD",
      "status": "Assessment completed",
      "accc_determination": "Approved",
      "is_waiver": true,
      "effective_notification_datetime": "2026-03-04T12:00:00Z",
      "determination_publication_date": "2026-03-10T12:00:00Z",
      "end_of_determination_period": null,
      "stage": "Waiver application",
      "acquirers": [
        {
          "name": "VC OPERATIONS (WA) PTY LTD",
          "identifier_type": "ABN",
          "identifier": "28 646 499 005"
        }
      ],
      "targets": [
        {
          "name": "The trustee for the Burke Family Trust",
          "identifier_type": "ABN",
          "identifier": "35 834 715 269"
        }
      ],
      "other_parties": [
        {
          "name": "VETS CENTRAL HOLDINGS PTY LTD",
          "identifier_type": "ABN",
          "identifier": "60 652 812 256"
        }
      ],
      "anzsic_codes": [
        {
          "code": "6970",
          "name": "Veterinary Services"
        },
        {
          "code": "9539",
          "name": "Other Personal Services n.e.c."
        }
      ],
      "url": "https://www.accc.gov.au/public-registers/mergers-and-acquisitions-registers/acquisitions-register/vets-central-%E2%80%93-west-toowoomba-veterinary-surgery-in-qld"
    }
  ],
  "page": 3,
  "page_size": 50,
  "total": 104,
  "total_pages": 3
}